{
  "manifestVersion": "3.1",
  "impls": {
    "521f46a3a370d5b34b11ea0752b914451da2805c065c72896cd96532e4d33a8b": {
      "address": "0x8F8350fd36B1Da9Cc1E92744C8D8186ae0215D3C",
      "txHash": "0x71da262c480ad6121feb9c2363fb53cef236c19c281a35de02926f4c336535d6",
      "layout": {
        "storage": [
          {
            "contract": "Initializable",
            "label": "_initialized",
            "type": "t_bool",
            "src": "../node_modules/@openzeppelin/contracts-upgradeable/proxy/Initializable.sol:24"
          },
          {
            "contract": "Initializable",
            "label": "_initializing",
            "type": "t_bool",
            "src": "../node_modules/@openzeppelin/contracts-upgradeable/proxy/Initializable.sol:29"
          },
          {
            "contract": "ContextUpgradeable",
            "label": "__gap",
            "type": "t_array(t_uint256)50_storage",
            "src": "../node_modules/@openzeppelin/contracts-upgradeable/GSN/ContextUpgradeable.sol:31"
          },
          {
            "contract": "AccessControlUpgradeable",
            "label": "_roles",
            "type": "t_mapping(t_bytes32,t_struct(RoleData)435_storage)",
            "src": "../node_modules/@openzeppelin/contracts-upgradeable/access/AccessControlUpgradeable.sol:61"
          },
          {
            "contract": "AccessControlUpgradeable",
            "label": "__gap",
            "type": "t_array(t_uint256)49_storage",
            "src": "../node_modules/@openzeppelin/contracts-upgradeable/access/AccessControlUpgradeable.sol:225"
          },
          {
            "contract": "ERC20Upgradeable",
            "label": "_balances",
            "type": "t_mapping(t_address,t_uint256)",
            "src": "../node_modules/@openzeppelin/contracts-upgradeable/token/ERC20/ERC20Upgradeable.sol:37"
          },
          {
            "contract": "ERC20Upgradeable",
            "label": "_allowances",
            "type": "t_mapping(t_address,t_mapping(t_address,t_uint256))",
            "src": "../node_modules/@openzeppelin/contracts-upgradeable/token/ERC20/ERC20Upgradeable.sol:39"
          },
          {
            "contract": "ERC20Upgradeable",
            "label": "_totalSupply",
            "type": "t_uint256",
            "src": "../node_modules/@openzeppelin/contracts-upgradeable/token/ERC20/ERC20Upgradeable.sol:41"
          },
          {
            "contract": "ERC20Upgradeable",
            "label": "_name",
            "type": "t_string_storage",
            "src": "../node_modules/@openzeppelin/contracts-upgradeable/token/ERC20/ERC20Upgradeable.sol:43"
          },
          {
            "contract": "ERC20Upgradeable",
            "label": "_symbol",
            "type": "t_string_storage",
            "src": "../node_modules/@openzeppelin/contracts-upgradeable/token/ERC20/ERC20Upgradeable.sol:44"
          },
          {
            "contract": "ERC20Upgradeable",
            "label": "_decimals",
            "type": "t_uint8",
            "src": "../node_modules/@openzeppelin/contracts-upgradeable/token/ERC20/ERC20Upgradeable.sol:45"
          },
          {
            "contract": "ERC20Upgradeable",
            "label": "__gap",
            "type": "t_array(t_uint256)44_storage",
            "src": "../node_modules/@openzeppelin/contracts-upgradeable/token/ERC20/ERC20Upgradeable.sol:312"
          },
          {
            "contract": "ERC20BurnableUpgradeable",
            "label": "__gap",
            "type": "t_array(t_uint256)50_storage",
            "src": "../node_modules/@openzeppelin/contracts-upgradeable/token/ERC20/ERC20BurnableUpgradeable.sol:50"
          },
          {
            "contract": "PausableUpgradeable",
            "label": "_paused",
            "type": "t_bool",
            "src": "../node_modules/@openzeppelin/contracts-upgradeable/utils/PausableUpgradeable.sol:28"
          },
          {
            "contract": "PausableUpgradeable",
            "label": "__gap",
            "type": "t_array(t_uint256)49_storage",
            "src": "../node_modules/@openzeppelin/contracts-upgradeable/utils/PausableUpgradeable.sol:96"
          },
          {
            "contract": "ERC20PausableUpgradeable",
            "label": "__gap",
            "type": "t_array(t_uint256)50_storage",
            "src": "../node_modules/@openzeppelin/contracts-upgradeable/token/ERC20/ERC20PausableUpgradeable.sol:37"
          },
          {
            "contract": "ERC20PresetMinterPauserUpgradeable",
            "label": "__gap",
            "type": "t_array(t_uint256)50_storage",
            "src": "../node_modules/@openzeppelin/contracts-upgradeable/presets/ERC20PresetMinterPauserUpgradeable.sol:101"
          },
          {
            "contract": "EnhancedMinterPauser",
            "label": "tokenTransferFeeDivisor",
            "type": "t_uint32",
            "src": "EnhancedMinterPauser.sol:21"
          },
          {
            "contract": "EnhancedMinterPauser",
            "label": "feeAddress",
            "type": "t_address",
            "src": "EnhancedMinterPauser.sol:24"
          },
          {
            "contract": "EnhancedMinterPauser",
            "label": "__gap",
            "type": "t_array(t_uint256)50_storage",
            "src": "EnhancedMinterPauser.sol:150"
          }
        ],
        "types": {
          "t_uint32": {
            "label": "uint32"
          },
          "t_address": {
            "label": "address"
          },
          "t_array(t_uint256)50_storage": {
            "label": "uint256[50]"
          },
          "t_bool": {
            "label": "bool"
          },
          "t_array(t_uint256)49_storage": {
            "label": "uint256[49]"
          },
          "t_mapping(t_address,t_uint256)": {
            "label": "mapping(address => uint256)"
          },
          "t_mapping(t_address,t_mapping(t_address,t_uint256))": {
            "label": "mapping(address => mapping(address => uint256))"
          },
          "t_uint256": {
            "label": "uint256"
          },
          "t_string_storage": {
            "label": "string"
          },
          "t_uint8": {
            "label": "uint8"
          },
          "t_array(t_uint256)44_storage": {
            "label": "uint256[44]"
          },
          "t_mapping(t_bytes32,t_struct(RoleData)435_storage)": {
            "label": "mapping(bytes32 => struct AccessControlUpgradeable.RoleData)"
          }
        }
      }
    }
  },
  "admin": {
    "address": "0x7aab82Eb8fB14aC34EAfafE76A27cE7e1614D193",
    "txHash": "0x1181e7155ede5ad715a16be424afcb38def86a48c63228147da146ff431f1efa"
  }
}
